README.txt
setup.py
asynchttplib.egg-info/PKG-INFO
asynchttplib.egg-info/SOURCES.txt
asynchttplib.egg-info/dependency_links.txt
asynchttplib.egg-info/requires.txt
asynchttplib.egg-info/top_level.txt
asynclib/__init__.py
asynclib/service.py
asynclib/amqp/__init__.py
asynclib/amqp/client.py
asynclib/amqp/server.py
asynclib/database/__init__.py
asynclib/database/mongo.py
asynclib/database/mongo_ref.py
asynclib/database/redis.py
asynclib/denorm_s/__init__.py
asynclib/denorm_s/db.py
asynclib/denorm_s/service.py
asynclib/http/__init__.py
asynclib/http/auth_lib.py
asynclib/http/error.py
asynclib/http/marshall.py
asynclib/http/parser.py
asynclib/http/rest.py
asynclib/utils/__init__.py
asynclib/utils/config.py
asynclib/utils/functions.py
asynclib/utils/loop.py
asynclib/utils/singleton.py