Metadata-Version: 1.0
Name: asynchttplib
Version: 0.3.2
Summary: Lib for creating microservice on asyncio
Home-page: UNKNOWN
Author: Oleksii Moisieienko
Author-email: me@alexmay23.com
License: MIT
Platform: UNKNOWN
